darwin-moea/__init__.py
darwin-moea/settings.py
darwin-moea/algorithm/__init__.py
darwin-moea/algorithm/moead.py
darwin-moea/algorithm/nsga2.py
darwin-moea/algorithm/tests/__init__.py
darwin-moea/algorithm/tests/moead_test.py
darwin-moea/algorithm/tests/nsga2_test.py
darwin-moea/ea/__init__.py
darwin-moea/ea/ea.py
darwin-moea/ea/ea_operation.py
darwin-moea/ea/individual.py
darwin-moea/ea/metrics.py
darwin-moea/ea/population.py
darwin-moea/ea/base/__init__.py
darwin-moea/ea/base/algorithm.py
darwin-moea/ea/base/crossover.py
darwin-moea/ea/base/decomposition.py
darwin-moea/ea/base/dominated.py
darwin-moea/ea/base/indicator.py
darwin-moea/ea/base/mutation.py
darwin-moea/ea/base/problem.py
darwin-moea/ea/base/select.py
darwin-moea/ea/indicator/__init__.py
darwin-moea/ea/indicator/gd.py
darwin-moea/ea/indicator/hv.py
darwin-moea/ea/indicator/igd.py
darwin-moea/ea/operation/__init__.py
darwin-moea/ea/operation/crossover/__init__.py
darwin-moea/ea/operation/crossover/simulated_binary_crossover.py
darwin-moea/ea/operation/dominated/__init__.py
darwin-moea/ea/operation/dominated/fast_non_dominated_sort.py
darwin-moea/ea/operation/dominated/tools.py
darwin-moea/ea/operation/mutation/__init__.py
darwin-moea/ea/operation/mutation/polynomial_mutation.py
darwin-moea/ea/operation/repair/__init__.py
darwin-moea/ea/operation/repair/bounds_back_repair.py
darwin-moea/ea/operation/repair/out_of_bounds_repair.py
darwin-moea/ea/operation/sampling/__init__.py
darwin-moea/ea/operation/sampling/random_sampling.py
darwin-moea/ea/operation/select/__init__.py
darwin-moea/ea/operation/select/optimal_selection.py
darwin-moea/ea/operation/select/tournament_selection.py
darwin-moea/ea/tests/__init__.py
darwin-moea/ea/tests/crowd_dis_test.py
darwin-moea/ea/tests/operation_test.py
darwin-moea/ea/tests/pop_test.py
darwin-moea/ea/util/__init__.py
darwin-moea/ea/util/module_loader.py
darwin-moea/ea/util/normalization.py
darwin-moea/ea/util/reference_direction.py
darwin_moea-0.0.4.dist-info/LICENSE
darwin_moea-0.0.4.dist-info/METADATA
darwin_moea-0.0.4.dist-info/WHEEL
darwin_moea-0.0.4.dist-info/entry_points.txt
darwin_moea-0.0.4.dist-info/top_level.txt
darwin_moea-0.0.4.dist-info/zip-safe
darwin_moea-0.0.4.dist-info/RECORD
