Metadata-Version: 2.1
Name: darwin-moea
Version: 0.0.4
Summary: A multi-objective optimization algorithm library implemented in Python, containing some basic operators and commonly used multi-objective optimization algorithms.
Home-page: https://github.com/qjdbfccc/darwin-moea.git
Author: qianjiduo
Author-email: 
License: MIT License
Project-URL: Source, https://github.com/qjdbfccc/darwin-moea.git
Classifier: Programming Language :: Python :: 3
Classifier: License :: OSI Approved :: MIT License
Classifier: Operating System :: OS Independent
Requires-Python: >=3.8
License-File: LICENSE
Requires-Dist: numpy
Requires-Dist: geatpy
Requires-Dist: scipy
